huaweicloudsdkgsl/__init__.py
huaweicloudsdkgsl/v3/__init__.py
huaweicloudsdkgsl/v3/gsl_async_client.py
huaweicloudsdkgsl/v3/gsl_client.py
huaweicloudsdkgsl/v3/model/__init__.py
huaweicloudsdkgsl/v3/model/add_network_switch_policy_request.py
huaweicloudsdkgsl/v3/model/add_network_switch_policy_response.py
huaweicloudsdkgsl/v3/model/add_or_modify_attribute_req.py
huaweicloudsdkgsl/v3/model/add_or_modify_tag_req.py
huaweicloudsdkgsl/v3/model/attribute_req.py
huaweicloudsdkgsl/v3/model/back_pool_mem_vo.py
huaweicloudsdkgsl/v3/model/back_pool_vo.py
huaweicloudsdkgsl/v3/model/batch_set_attributes_req.py
huaweicloudsdkgsl/v3/model/batch_set_attributes_request.py
huaweicloudsdkgsl/v3/model/batch_set_attributes_response.py
huaweicloudsdkgsl/v3/model/batch_set_tags_req.py
huaweicloudsdkgsl/v3/model/batch_set_tags_request.py
huaweicloudsdkgsl/v3/model/batch_set_tags_response.py
huaweicloudsdkgsl/v3/model/cm_attribute_vo.py
huaweicloudsdkgsl/v3/model/cm_tag_vo.py
huaweicloudsdkgsl/v3/model/create_attribute_request.py
huaweicloudsdkgsl/v3/model/create_attribute_response.py
huaweicloudsdkgsl/v3/model/create_send_sms_req.py
huaweicloudsdkgsl/v3/model/create_tag_request.py
huaweicloudsdkgsl/v3/model/create_tag_response.py
huaweicloudsdkgsl/v3/model/cut_net_req.py
huaweicloudsdkgsl/v3/model/delete_real_name_request.py
huaweicloudsdkgsl/v3/model/delete_real_name_response.py
huaweicloudsdkgsl/v3/model/delete_tag_request.py
huaweicloudsdkgsl/v3/model/delete_tag_response.py
huaweicloudsdkgsl/v3/model/disable_attribute_request.py
huaweicloudsdkgsl/v3/model/disable_attribute_response.py
huaweicloudsdkgsl/v3/model/down_up_time_for_sim_card_req.py
huaweicloudsdkgsl/v3/model/enable_attribute_request.py
huaweicloudsdkgsl/v3/model/enable_attribute_response.py
huaweicloudsdkgsl/v3/model/enable_sim_card_request.py
huaweicloudsdkgsl/v3/model/enable_sim_card_response.py
huaweicloudsdkgsl/v3/model/exceed_cut_net_req.py
huaweicloudsdkgsl/v3/model/flow_usage_vo.py
huaweicloudsdkgsl-3.1.184.dist-info/METADATA
huaweicloudsdkgsl-3.1.184.dist-info/WHEEL
huaweicloudsdkgsl-3.1.184.dist-info/licenses/LICENSE
huaweicloudsdkgsl-3.1.184.dist-info/RECORD
